[
  {
    "id": 1,
    "image": "/images/Webstudio.png",
    "title": "Webstudio",
    "github": "https://github.com/AlexTkachenkoFullstack/Webstudio",
    "demo": "https://alextkachenkofullstack.github.io/Webstudio/"
  },
  {
    "id": 2,
    "image": "/images/Ice-cream.png",
    "title": "Ice-cream",
    "github": "https://github.com/AlexTkachenkoFullstack/ice-cream",
    "demo": "https://alextkachenkofullstack.github.io/ice-cream/"
  },
  {
    "id": 3,
    "image": "/images/Bookshelf.png",
    "title": "Bookshelf",
    "github": "https://github.com/AlexTkachenkoFullstack/bookshelf",
    "demo": "https://bookshelf-for-you.netlify.app/"
  },
  {
    "id": 4,
    "image": "/images/Phonebook.png",
    "title": "Phonebook app",
    "github": "https://github.com/AlexTkachenkoFullstack/your-phonebook",
    "demo": "https://alextkachenkofullstack.github.io/your-phonebook/"
  },
  {
    "id": 5,
    "image": "/images/Movie.jpg",
    "title": "Movie-mania",
    "github": "https://github.com/AlexTkachenkoFullstack/movie-mania",
    "demo": "https://alextkachenkofullstack.github.io/movie-mania/"
  },
  {
    "id": 6,
    "image": "/images/Healthy-hub.png",
    "title": "Healthy-hub",
    "github": "https://github.com/AlexTkachenkoFullstack/healthy-hub",
    "demo": "https://alextkachenkofullstack.github.io/healthy-hub/"
  },
  {
    "id": 7,
    "image": "/images/Auto-rent.png",
    "title": "Auro-rent",
    "github": "https://github.com/AlexTkachenkoFullstack/rent-car",
    "demo": "https://alextkachenkofullstack.github.io/rent-car/"
  }
]